mcstools/__init__.py
mcstools/conftest.py
mcstools/data_path_handler.py
mcstools/detector_positions.py
mcstools/loader.py
mcstools/mcsfile.py
mcstools/radiance_profile.py
mcstools/reader.py
mcstools/test_data_path_handler.py
mcstools/test_mcsfile.py
mcstools/test_radiance_profile.py
mcstools/test_reader.py
mcstools/plotting/l1b_panel.py
mcstools/preprocess/__init__.py
mcstools/preprocess/data_pipeline.py
mcstools/preprocess/l1b.py
mcstools/preprocess/onplanet_finder.py
mcstools/preprocess/l2/dev.ipynb
mcstools/preprocess/l2/filter_and_bin.py
mcstools/util/__init__.py
mcstools/util/geom.py
mcstools/util/io.py
mcstools/util/log.py
mcstools/util/test_util.py
mcstools/util/time.py
mcstools-0.5.0.dist-info/METADATA
mcstools-0.5.0.dist-info/WHEEL
mcstools-0.5.0.dist-info/licenses/LICENSE
mcstools-0.5.0.dist-info/RECORD
