Metadata-Version: 2.4
Name: mcstools
Version: 0.5.0
Summary: Read, load, and process Mars Climate Sounder data
License-File: LICENSE
Keywords: mars, mcs
Requires-Python: >=3.10
Requires-Dist: cmcrameri>=1.9
Requires-Dist: coloredlogs>=15.0.1
Requires-Dist: hvplot>=0.11.3
Requires-Dist: mars-time
Requires-Dist: numpy>=2.2.6
Requires-Dist: pandas>=2.3.0
Requires-Dist: panel>=1.7.1
Requires-Dist: python-dotenv>=1.1.0
Requires-Dist: requests>=2.32.4
Requires-Dist: scipy>=1.15.3
Requires-Dist: xarray>=2025.6.1
